cliyaml/__init__.py
cliyaml/cli.py
cliyaml/parse.py
cliyaml/regexp.py
cliyaml/source.py
cliyaml-0.1.2.dist-info/licenses/LICENSE
cliyaml-0.1.2.dist-info/WHEEL
cliyaml-0.1.2.dist-info/METADATA
cliyaml-0.1.2.dist-info/RECORD
