Metadata-Version: 2.4
Name: cliyaml
Version: 0.1.2
Summary: Prototype projects fast with YAML configuration
Author: Thibaut de Saivre
Author-email: Thibaut de Saivre <thibaut2saivre@gmail.com>
License-Expression: MIT
License-File: LICENSE
Classifier: Programming Language :: Python :: 3
Classifier: Operating System :: OS Independent
Requires-Python: >=3.12
Project-URL: Homepage, https://github.com/GnRlLeclerc/cliyaml
